swiss_army_keras/DejaVuSansMono.ttf
swiss_army_keras/__init__.py
swiss_army_keras/_backbone_zoo.py
swiss_army_keras/_model_att_unet_2d.py
swiss_army_keras/_model_classifier.py
swiss_army_keras/_model_deeplab_v3_plus.py
swiss_army_keras/_model_r2_unet_2d.py
swiss_army_keras/_model_resunet_a_2d.py
swiss_army_keras/_model_swin_unet_2d.py
swiss_army_keras/_model_transunet_2d.py
swiss_army_keras/_model_u2net_2d.py
swiss_army_keras/_model_unet_2d.py
swiss_army_keras/_model_unet_3plus_2d.py
swiss_army_keras/_model_unet_plus_2d.py
swiss_army_keras/_model_vnet_2d.py
swiss_army_keras/activations.py
swiss_army_keras/backbones.py
swiss_army_keras/base.py
swiss_army_keras/dataset_utils.py
swiss_army_keras/layer_utils.py
swiss_army_keras/losses.py
swiss_army_keras/metrics.py
swiss_army_keras/models.py
swiss_army_keras/optimizers.py
swiss_army_keras/quantization_utils.py
swiss_army_keras/training_utils.py
swiss_army_keras/transformer_layers.py
swiss_army_keras/utils.py
swiss_army_keras-0.10.0.dist-info/LICENSE
swiss_army_keras-0.10.0.dist-info/METADATA
swiss_army_keras-0.10.0.dist-info/WHEEL
swiss_army_keras-0.10.0.dist-info/top_level.txt
swiss_army_keras-0.10.0.dist-info/RECORD
